pure_protobuf/__init__.py
pure_protobuf/_accumulators.py
pure_protobuf/_mergers.py
pure_protobuf/annotations.py
pure_protobuf/descriptors/__init__.py
pure_protobuf/descriptors/_field.py
pure_protobuf/descriptors/record.py
pure_protobuf/exceptions.py
pure_protobuf/helpers/__init__.py
pure_protobuf/helpers/_dataclasses.py
pure_protobuf/helpers/_typing.py
pure_protobuf/helpers/datetime.py
pure_protobuf/helpers/io.py
pure_protobuf/helpers/itertools.py
pure_protobuf/interfaces/__init__.py
pure_protobuf/interfaces/_repr.py
pure_protobuf/interfaces/_skip.py
pure_protobuf/interfaces/_vars.py
pure_protobuf/interfaces/accumulate.py
pure_protobuf/interfaces/merge.py
pure_protobuf/interfaces/read.py
pure_protobuf/interfaces/write.py
pure_protobuf/io/__init__.py
pure_protobuf/io/bytes_.py
pure_protobuf/io/fixed32.py
pure_protobuf/io/fixed64.py
pure_protobuf/io/struct_.py
pure_protobuf/io/tag.py
pure_protobuf/io/url.py
pure_protobuf/io/varint.py
pure_protobuf/io/wire_type.py
pure_protobuf/io/wrappers.py
pure_protobuf/message.py
pure_protobuf/one_of.py
pure_protobuf/py.typed
pure_protobuf/well_known.py
pure_protobuf-3.1.4.dist-info/LICENSE
pure_protobuf-3.1.4.dist-info/METADATA
pure_protobuf-3.1.4.dist-info/WHEEL
pure_protobuf-3.1.4.dist-info/RECORD
