Metadata-Version: 2.3
Name: pure-protobuf
Version: 3.1.4
Summary: Protocol Buffers using Python type annotations
License: MIT
Keywords: protobuf,protocol-buffers
Author: Pavel Perestoronin
Author-email: eigenein@gmail.com
Requires-Python: >=3.9.0,<4.0.0
Classifier: Development Status :: 5 - Production/Stable
Classifier: Intended Audience :: Developers
Classifier: License :: OSI Approved :: MIT License
Classifier: Operating System :: OS Independent
Classifier: Programming Language :: Python :: 3
Classifier: Programming Language :: Python :: 3.9
Classifier: Programming Language :: Python :: 3.10
Classifier: Programming Language :: Python :: 3.11
Classifier: Programming Language :: Python :: 3.12
Classifier: Programming Language :: Python :: 3.13
Classifier: Programming Language :: Python :: 3 :: Only
Classifier: Topic :: Software Development :: Libraries
Classifier: Topic :: Software Development :: Libraries :: Python Modules
Classifier: Typing :: Typed
Requires-Dist: get-annotations (>=0.1.2,<0.2.0) ; python_version < "3.10"
Requires-Dist: typing-extensions (>=4.4.0,<5.0.0)
Project-URL: Changelog, https://github.com/eigenein/protobuf/blob/master/CHANGELOG.md
Project-URL: Homepage, https://github.com/eigenein/protobuf
Project-URL: Issues, https://github.com/eigenein/protobuf/issues
Project-URL: Repository, https://github.com/eigenein/protobuf
